reasoners/__init__.py
reasoners/base.py
reasoners/utils.py
reasoners/algorithm/__init__.py
reasoners/algorithm/beam_search.py
reasoners/algorithm/dfs.py
reasoners/algorithm/greedy.py
reasoners/algorithm/mcts.py
reasoners/algorithm/random.py
reasoners/benchmark/README.md
reasoners/benchmark/__init__.py
reasoners/benchmark/aqua.py
reasoners/benchmark/blocksworld.py
reasoners/benchmark/bw_utils.py
reasoners/benchmark/gsm8k.py
reasoners/benchmark/hotpotqa.py
reasoners/benchmark/prontoqa.py
reasoners/lm/README.md
reasoners/lm/__init__.py
reasoners/lm/anthropic_model.py
reasoners/lm/exllama_model.py
reasoners/lm/gemini_model.py
reasoners/lm/hf_model.py
reasoners/lm/llama_2_model.py
reasoners/lm/llama_3_model.py
reasoners/lm/llama_cpp_model.py
reasoners/lm/llama_model.py
reasoners/lm/openai_hf_model.py
reasoners/lm/openai_model.py
reasoners/tools/__init__.py
reasoners/tools/tools.py
reasoners/tools/wikiutils.py
reasoners/visualization/__init__.py
reasoners/visualization/__main__.py
reasoners/visualization/tree_log.py
reasoners/visualization/tree_snapshot.py
reasoners/visualization/visualizer_client.py
llm_reasoners-1.0.2.dist-info/LICENSE
llm_reasoners-1.0.2.dist-info/METADATA
llm_reasoners-1.0.2.dist-info/WHEEL
llm_reasoners-1.0.2.dist-info/entry_points.txt
llm_reasoners-1.0.2.dist-info/top_level.txt
llm_reasoners-1.0.2.dist-info/RECORD
